G5toA4/__init__.py
G5toA4/__main__.py
g5toa4-0.3.dist-info/METADATA
g5toa4-0.3.dist-info/WHEEL
g5toa4-0.3.dist-info/licenses/LICENSE
g5toa4-0.3.dist-info/RECORD
