Metadata-Version: 2.1
Name: G5toA4
Version: 0.3
Summary: Convert G5 book PDF into a A4, maintaining the real sizes.
Project-URL: Homepage, https://github.com/MassimoGirondi/G5toA4
Project-URL: Issues, https://github.com/MassimoGirondi/G5toA4/issues
Author-email: Massimo Girondi <girondi@kth.se>
License:                     GNU GENERAL PUBLIC LICENSE
License-File: LICENSE
Classifier: License :: OSI Approved :: GNU General Public License v3 (GPLv3)
Classifier: Operating System :: OS Independent
Classifier: Programming Language :: Python :: 3
Requires-Python: >=3.6
